MANIFEST.in
README.txt
setup.py
django_ninjapaginator_ng.egg-info/PKG-INFO
django_ninjapaginator_ng.egg-info/SOURCES.txt
django_ninjapaginator_ng.egg-info/dependency_links.txt
django_ninjapaginator_ng.egg-info/not-zip-safe
django_ninjapaginator_ng.egg-info/requires.txt
django_ninjapaginator_ng.egg-info/top_level.txt
ninjapaginator/__init__.py
ninjapaginator/util.py
ninjapaginator/templates/paginator.html
ninjapaginator/templates/paginator_digg.html
ninjapaginator/templates/paginator_filmfeed.html
ninjapaginator/templates/paginator_muzx.html
ninjapaginator/templatetags/__init__.py
ninjapaginator/templatetags/paginator.py