Metadata-Version: 1.0
Name: django-ninjapaginator-ng
Version: 0.1.6
Summary: Django application with multiple type of pagination integrated
Home-page: http://bitbucket.org/barbuza/django-ninjapaginator/
Author: Anderson
Author-email: self.anderson@gmail.com
License: BSD
Keywords: django
Platform: UNKNOWN
